teste_bibliot/__init__.py
teste_bibliot/funcoes.py
teste_cursofiap_wbb-1.0.2.dist-info/METADATA
teste_cursofiap_wbb-1.0.2.dist-info/WHEEL
teste_cursofiap_wbb-1.0.2.dist-info/top_level.txt
teste_cursofiap_wbb-1.0.2.dist-info/RECORD
