Metadata-Version: 2.1
Name: teste-cursofiap-wbb
Version: 1.0.2
Summary: Teste de criação de lib curso fiap WBB
Home-page: 
Author: William Brandão Bilatto
Author-email: williambilatto@gmail.com
License: MIT
